[
 {
  "id": "england-irs-2016-2025",
  "jurisdiction": "England",
  "period": "2016–H1 2025",
  "count": 468,
  "confirmedPvOrigin": null,
  "metric": "Attended fires with solar/PV terms in incident free text",
  "sourceClass": "Official national incident statistics",
  "sourceTitle": "MHCLG Incident Recording System, Table A37",
  "sourceUrl": "https://www.gov.uk/government/statistics/number-of-fires-in-england-with-solar-panel-or-photovoltaic-panel-mentioned-in-the-additional-information-free-text",
  "windowRelation": "within-window",
  "caveat": "A PV term may describe presence rather than ignition. Free-text search is neither complete nor proof of causation.",
  "yearly": {
   "2016": 30,
   "2017": 31,
   "2018": 27,
   "2019": 26,
   "2020": 39,
   "2021": 64,
   "2022": 43,
   "2023": 68,
   "2024": 81,
   "2025": 59
  }
 },
 {
  "id": "uk-qbe-foi-2022-2024",
  "jurisdiction": "United Kingdom",
  "period": "2022–2024",
  "count": 406,
  "confirmedPvOrigin": null,
  "metric": "Fire-service incidents involving a solar panel",
  "sourceClass": "Insurer FOI compilation",
  "sourceTitle": "QBE UK fire-service FOI research",
  "sourceUrl": "https://qbeeurope.com/news-and-events/press-releases/uk-fire-services-tackle-a-solar-panel-fire-every-two-days/",
  "windowRelation": "within-window",
  "caveat": "Overlaps England IRS data and must not be added to it. QBE reports 107 incidents in 2022, 128 in 2023 and 171 in 2024.",
  "yearly": {
   "2022": 107,
   "2023": 128,
   "2024": 171
  }
 },
 {
  "id": "netherlands-tno-2022-2023",
  "jurisdiction": "Netherlands",
  "period": "2022–2023",
  "count": 152,
  "confirmedPvOrigin": 30,
  "metric": "Building fires where a solar-energy system was present",
  "sourceClass": "National technical research",
  "sourceTitle": "TNO / NIPV / NEN building-fire study",
  "sourceUrl": "https://www.tno.nl/en/newsroom/2024/11/building-fires-solar-panels-first-study/",
  "windowRelation": "within-window",
  "caveat": "Of 152 fires, 70 were investigated further: 30 originated in the solar system, 29 did not and 11 remained unknown.",
  "yearly": null
 },
 {
  "id": "nsw-frnsw-2018-2020",
  "jurisdiction": "New South Wales, Australia",
  "period": "2018–2020",
  "count": 217,
  "confirmedPvOrigin": null,
  "metric": "Fire incidents associated with solar panels",
  "sourceClass": "Regulator consultation citing Fire and Rescue NSW",
  "sourceTitle": "Energy Safe Victoria DC-isolator consultation",
  "sourceUrl": "https://www.energysafe.vic.gov.au/sites/default/files/2022-12/Consultation_DC_Isolators_Sep2021.pdf",
  "windowRelation": "within-window",
  "caveat": "Annual figures were 22 in 2018, 56 in 2019 and 139 in 2020. Association does not necessarily mean PV ignition.",
  "yearly": {
   "2018": 22,
   "2019": 56,
   "2020": 139
  }
 },
 {
  "id": "victoria-cfa-2015-2020",
  "jurisdiction": "Regional Victoria, Australia",
  "period": "2015–2020",
  "count": 188,
  "confirmedPvOrigin": 65,
  "metric": "Fires involving solar installations",
  "sourceClass": "Regulator consultation citing Country Fire Authority",
  "sourceTitle": "Energy Safe Victoria DC-isolator consultation",
  "sourceUrl": "https://www.energysafe.vic.gov.au/sites/default/files/2022-12/Consultation_DC_Isolators_Sep2021.pdf",
  "windowRelation": "overlaps-window",
  "caveat": "The period starts before the dashboard window. CFA believed DC isolators caused 65 of the 188 incidents.",
  "yearly": null
 },
 {
  "id": "victoria-mfb-2014-2019",
  "jurisdiction": "Metropolitan Melbourne, Australia",
  "period": "2014–Jan 2019",
  "count": 48,
  "confirmedPvOrigin": 48,
  "metric": "Fires where the PV system was considered the cause",
  "sourceClass": "Regulator consultation citing Fire Rescue Victoria/MFB",
  "sourceTitle": "Energy Safe Victoria DC-isolator consultation",
  "sourceUrl": "https://www.energysafe.vic.gov.au/sites/default/files/2022-12/Consultation_DC_Isolators_Sep2021.pdf",
  "windowRelation": "overlaps-window",
  "caveat": "The period starts before the dashboard window; 41 incidents (85%) were believed caused by DC isolators.",
  "yearly": null
 },
 {
  "id": "uk-bre-2015-2018",
  "jurisdiction": "United Kingdom",
  "period": "Historical + Jul 2015–Feb 2018",
  "count": 80,
  "confirmedPvOrigin": 58,
  "metric": "Unique potential PV-related incidents investigated",
  "sourceClass": "Government-funded forensic research",
  "sourceTitle": "BRE Fire and Solar PV Systems—Investigations and Evidence",
  "sourceUrl": "https://www.gov.uk/government/publications/fire-incidents-involving-solar-panels",
  "windowRelation": "overlaps-window",
  "caveat": "Includes 33 historical incidents. Of 80 records, 16 were not caused by PV and six were unknown; 22 PV-caused events were serious and 36 localized or thermal.",
  "yearly": null
 },
 {
  "id": "germany-fraunhofer-historical",
  "jurisdiction": "Germany",
  "period": "Approximately 1993–2013",
  "count": 350,
  "confirmedPvOrigin": 120,
  "metric": "Fires involving PV systems",
  "sourceClass": "National research institute",
  "sourceTitle": "Fraunhofer ISE fire-protection research",
  "sourceUrl": "https://www.ise.fraunhofer.de/en/press-media/press-releases/2013/fire-protection-in-photovoltaic-systems.html",
  "windowRelation": "historical-benchmark",
  "caveat": "Outside the dashboard's ten-year window; retained only as a benchmark and never included in current-period totals.",
  "yearly": null
 },
 {
  "id": "japan-csic-2008-2017",
  "jurisdiction": "Japan",
  "period": "2008–Nov 2017",
  "count": 127,
  "confirmedPvOrigin": 13,
  "metric": "Residential PV systems reported smoking or catching fire",
  "sourceClass": "Consumer-safety investigation",
  "sourceTitle": "Japan Consumer Safety Investigation Commission findings",
  "sourceUrl": "https://www.pvel.com/wp-content/uploads/PVEL-HelioVolta-Ultimate-Safety-Guide-for-Solar-PV-Connectors-Feb-2022.pdf",
  "windowRelation": "overlaps-window",
  "caveat": "Most of the reporting period predates the dashboard window. Thirteen examined cases involved fire from modules or cables; seven spread to the roof.",
  "yearly": null
 },
 {
  "id": "us-walmart-tesla-2012-2018",
  "jurisdiction": "United States",
  "period": "2012–2018",
  "count": 7,
  "confirmedPvOrigin": null,
  "metric": "Walmart store fires attributed to rooftop solar in the retailer's complaint",
  "sourceClass": "Primary court filing",
  "sourceTitle": "Walmart Inc. v. Tesla Inc. complaint",
  "sourceUrl": "https://s3.documentcloud.org/documents/6306645/Gov-Uscourts-654765-2019-1-0.pdf",
  "windowRelation": "overlaps-window",
  "caveat": "These are allegations from settled litigation, not seven independent official cause determinations. One 2012 incident falls outside the current window; the six newer locations are also represented as reported case records and must not be double-counted.",
  "yearly": {
   "2012": 1,
   "2016": 1,
   "2017": 1,
   "2018": 4
  }
 },
 {
  "id": "north-america-amazon-solar-2020-2021",
  "jurisdiction": "North American Amazon facilities",
  "period": "Apr 2020–Jun 2021",
  "count": 6,
  "confirmedPvOrigin": null,
  "metric": "Critical fire or arc-flash events in Amazon's internal solar-facility review",
  "sourceClass": "Investigative reporting from internal records",
  "sourceTitle": "CNBC investigation of Amazon rooftop-solar shutdown",
  "sourceUrl": "https://www.cnbc.com/2022/09/01/amazon-took-solar-rooftops-offline-last-year-after-fires-explosions.html",
  "windowRelation": "within-window",
  "caveat": "CNBC reported six events among 47 applicable North American sites (12.7%). The other locations were not publicly disclosed, so this portfolio count is not converted into six map pins and may overlap the Perryville case.",
  "yearly": null
 },
 {
  "id": "us-nfirs-pv-coding-limitation",
  "jurisdiction": "United States",
  "period": "NFIRS public releases through 2024",
  "count": null,
  "confirmedPvOrigin": null,
  "metric": "No defensible national PV-fire total from the public NFIRS coding fields",
  "sourceClass": "Official federal data limitation",
  "sourceTitle": "U.S. Fire Administration NFIRS Complete Reference Guide",
  "sourceUrl": "https://www.usfa.fema.gov/downloads/pdf/nfirs/nfirs_complete_reference_guide_2015.pdf",
  "windowRelation": "within-window",
  "caveat": "NFIRS code 115 records solar panels only as an optional factor affecting suppression, not as equipment or cause of ignition. Generic equipment codes for wiring, panels, disconnects and inverters do not identify a PV system, so raw NFIRS cannot cleanly count PV-origin fires.",
  "yearly": null
 },
 {
  "id": "us-doe-pv-fire-data-gap",
  "jurisdiction": "United States",
  "period": "Current federal guidance",
  "count": null,
  "confirmedPvOrigin": null,
  "metric": "National rooftop-PV fire count tracked by the U.S. Fire Administration",
  "sourceClass": "Official federal safety guidance",
  "sourceTitle": "U.S. Department of Energy guide to fire safety in solar systems",
  "sourceUrl": "https://www.energy.gov/cmei/systems/guide-fire-safety-solar-systems",
  "windowRelation": "within-window",
  "caveat": "DOE states that the U.S. Fire Administration does not track the number of fires caused by rooftop PV systems. It also distinguishes PV-origin fires from ordinary building fires that later involve a PV-covered roof.",
  "yearly": null
 },
 {
  "id": "italy-cnvvf-2015-2024",
  "jurisdiction": "Italy",
  "period": "2015–2024",
  "count": null,
  "confirmedPvOrigin": null,
  "metric": "PV-panel fire incidents in the national fire brigade statistical database; roughly 5–13 fires per GW installed annually",
  "sourceClass": "Official national incident statistics",
  "sourceTitle": "CNVVF statistical database, analysed in Rus et al. 2025 (J. Phys.: Conf. Ser. 3121 012050)",
  "sourceUrl": "https://iopscience.iop.org/article/10.1088/1742-6596/3121/1/012050",
  "windowRelation": "within-window",
  "caveat": "A dedicated “Photovoltaic Panels” category exists since 2014. Counts reflect incidents where PV modules were involved in the fire, not proof that PV caused it. Earlier surveys recorded roughly 2,500 PV-related incidents across ~550,000 systems for 2002–2015.",
  "yearly": null
 },
 {
  "id": "slovenia-urszr-2023-2024",
  "jurisdiction": "Slovenia",
  "period": "May 2023–Jul 2024",
  "count": null,
  "confirmedPvOrigin": null,
  "metric": "PV-related fire deployments reported to the 112 emergency system; roughly 37 fires per GW installed annually",
  "sourceClass": "Official national incident statistics",
  "sourceTitle": "URSZR incident reporting, analysed in Rus et al. 2025 (J. Phys.: Conf. Ser. 3121 012050)",
  "sourceUrl": "https://iopscience.iop.org/article/10.1088/1742-6596/3121/1/012050",
  "windowRelation": "within-window",
  "caveat": "A PV-related category was only added to the reporting form in mid-2023, so the observation window is short and annual figures are extrapolated. Inclusion criteria may capture fires where a PV system was present but not the ignition source.",
  "yearly": null
 },
 {
  "id": "international-benchmark-29-per-gw",
  "jurisdiction": "International (AU, DE, IT, US)",
  "period": "Multi-year, harmonised",
  "count": null,
  "confirmedPvOrigin": null,
  "metric": "Weighted international average of ~29 PV-related fires per GW of installed capacity per year",
  "sourceClass": "Peer-reviewed comparative research",
  "sourceTitle": "Four-country comparative study, reaffirmed in Rus et al. 2025 (J. Phys.: Conf. Ser. 3121 012050)",
  "sourceUrl": "https://iopscience.iop.org/article/10.1088/1742-6596/3121/1/012050",
  "windowRelation": "context-benchmark",
  "caveat": "National methodologies differ substantially and had to be harmonised; the benchmark expresses reporting frequency relative to installed capacity, not comparative safety of products or installers.",
  "yearly": null
 },
 {
  "id": "denmark-brs-2020-2025",
  "jurisdiction": "Denmark",
  "period": "2020–H1 2025",
  "count": 190,
  "confirmedPvOrigin": null,
  "metric": "Emergency-response incidents involving PV systems recorded by Beredskabsstyrelsen",
  "sourceClass": "Official national incident statistics",
  "sourceTitle": "Beredskabsstyrelsen: Flere solcelleanlæg betyder ikke nødvendigvis flere brande",
  "sourceUrl": "https://www.brs.dk/da/nyheder/2025/flere-solcelleanlag-betyder-ikke-nodvendigvis-flere-brande/",
  "windowRelation": "within-window",
  "caveat": "Incident involvement of a PV system does not establish the PV system as the ignition source; the agency notes fire counts have not grown in step with installations."
 },
 {
  "id": "sweden-msb-2018-2024",
  "jurisdiction": "Sweden",
  "period": "2018–2024",
  "count": 155,
  "confirmedPvOrigin": null,
  "metric": "Fires and fire incidents linked to solar-cell installations in rescue-service incident reports",
  "sourceClass": "Fire-service incident statistics",
  "sourceTitle": "Statistik om bränder i solcellsanläggningar (Swedish rescue-service data compilation)",
  "sourceUrl": "https://www.utkiken.net/solceller/77813-statistik-om-br%C3%A4nder-i-solcellsanl%C3%A4ggningar",
  "windowRelation": "within-window",
  "caveat": "Compiled from MSB incident-report free text; classification of PV as cause versus involvement varies across municipal rescue services."
 },
 {
  "id": "poland-kgpsp-2024-2026",
  "jurisdiction": "Poland",
  "period": "2024–Q1 2026",
  "count": 1676,
  "confirmedPvOrigin": null,
  "metric": "Fires in buildings or facilities with PV installations recorded by the State Fire Service (KG PSP): 808 in 2024, 759 in 2025 (to 10 Nov), 109 in Q1 2026",
  "sourceClass": "Official national fire-service statistics",
  "sourceTitle": "KG PSP data reported by Gram w Zielone: Pożary fotowoltaiki",
  "sourceUrl": "https://www.gramwzielone.pl/energia-sloneczna/20366952/pozar-fotowoltaiki-na-dolnym-slasku-strazacy-nie-mogli-odlaczyc-instalacji",
  "windowRelation": "within-window",
  "caveat": "Counts are fires in objects where a PV installation was present, not necessarily fires ignited by the PV system."
 },
 {
  "id": "czechia-hzs-2015-2024",
  "jurisdiction": "Czechia",
  "period": "2015–2024",
  "count": 167,
  "confirmedPvOrigin": 59,
  "metric": "Fires involving PV power plants recorded by the Czech fire service (HZS ČR); 83 in 2024 alone, of which 59 caused by the PV system",
  "sourceClass": "Official national fire-service statistics",
  "sourceTitle": "HZS ČR data reported by Novinky.cz: V Česku výrazně roste počet požárů fotovoltaických elektráren",
  "sourceUrl": "https://www.novinky.cz/clanek/krimi-v-cesku-vyrazne-roste-pocet-pozaru-fotovoltaickych-elektraren-mohou-za-to-i-lonske-povodne-40510124",
  "windowRelation": "within-window",
  "caveat": "confirmedPvOrigin figure applies to 2024 only; earlier-year cause attribution is not broken out in the report."
 },
 {
  "id": "japan-nite-2015-2024",
  "jurisdiction": "Japan",
  "period": "FY2015–FY2024",
  "count": 260,
  "confirmedPvOrigin": 239,
  "metric": "Accidents involving solar power generation equipment reported to NITE over 10 years; about 90% (239) were fires, with power conditioners (170 cases) the leading component",
  "sourceClass": "Official product-safety statistics",
  "sourceTitle": "NITE mail magazine Vol.487: 太陽光発電設備の事故",
  "sourceUrl": "https://www.nite.go.jp/jiko/chuikanki/mailmagazin/2025fy/vol487_251028.html",
  "windowRelation": "within-window",
  "caveat": "NITE receives reports on consumer-product accidents; utility-scale plant fires outside the reporting scheme are not captured."
 },
 {
  "id": "south-korea-nfa-2019-2023",
  "jurisdiction": "South Korea",
  "period": "2019–2023",
  "count": 472,
  "confirmedPvOrigin": null,
  "metric": "PV-related fires recorded by the National Fire Agency: 62 (2019), 69 (2020), 81 (2021), 99 (2022), 124 (2023); ~7 in 10 attributed to electrical factors",
  "sourceClass": "Official national fire-service statistics",
  "sourceTitle": "National Fire Agency data reported by Newsis: 최근 5년 태양광 화재 44억 피해",
  "sourceUrl": "https://mobile.newsis.com/view_amp.html?ar_id=NISX20231006_0002474575",
  "windowRelation": "within-window",
  "caveat": "Aggregate includes fires at PV facilities of all scales; electrical-factor attribution does not distinguish module, inverter, or wiring origin."
 },
 {
  "id": "new-zealand-fenz-2020-2025",
  "jurisdiction": "New Zealand",
  "period": "FY2020–FY2025",
  "count": 2,
  "confirmedPvOrigin": null,
  "metric": "Solar-panel structure fires in Fire and Emergency NZ callout data released under the Official Information Act",
  "sourceClass": "Official information release",
  "sourceTitle": "FENZ OIA response 19266: Callout data for solar-related fires",
  "sourceUrl": "https://www.fireandemergency.nz/assets/Documents/OIA-responses/OIA19266-Callout-data-for-solar-related-fires.pdf",
  "windowRelation": "within-window",
  "caveat": "Callout coding relies on attending crews recording solar involvement; low counts partly reflect NZ's small installed base."
 },
 {
  "id": "victoria-esv-2021-2023",
  "jurisdiction": "Victoria, Australia",
  "period": "FY2021–22–FY2022–23",
  "count": 82,
  "confirmedPvOrigin": null,
  "metric": "Solar panel-related fires reported to Energy Safe Victoria: 27 (2021–22) rising to 55 (2022–23); DC-isolator fires rose from 15 to 41",
  "sourceClass": "Official energy-safety regulator statistics",
  "sourceTitle": "ABC News: Solar panel fires increase prompts DC isolator warning",
  "sourceUrl": "https://www.abc.net.au/news/2023-09-14/solar-panel-fires-increase-dc-isolator-nt-worksafe-warning/102843552",
  "windowRelation": "within-window",
  "caveat": "Complements the CFA/MFB brigade series already tracked; regulator reporting captures notified electrical incidents rather than all brigade callouts."
 },
 {
  "id": "lower-austria-bv-2019-2025",
  "jurisdiction": "Lower Austria, Austria",
  "period": "2019–2025",
  "count": 27,
  "confirmedPvOrigin": null,
  "metric": "Documented fire cases involving PV systems out of roughly 145,000 installed systems in the province",
  "sourceClass": "Provincial fire-prevention authority",
  "sourceTitle": "ORF Niederösterreich: PV-Anlagen – Montagemängel als Brandrisiko (Landesstelle für Brandverhütung)",
  "sourceUrl": "https://noe.orf.at/stories/3319472/",
  "windowRelation": "within-window",
  "caveat": "The fire-prevention office highlights installation defects as the dominant cause; only investigated cases are counted."
 },
 {
  "id": "france-aria-2002-2016",
  "jurisdiction": "France",
  "period": "2002–2016",
  "count": 53,
  "confirmedPvOrigin": null,
  "metric": "Incidents involving photovoltaic panels recorded in the national ARIA industrial-accident database",
  "sourceClass": "Official accident database study",
  "sourceTitle": "Ministère de la Transition écologique, base ARIA: Accidentologie photovoltaïque",
  "sourceUrl": "https://www.aria.developpement-durable.gouv.fr/wp-content/uploads/2016/02/2016-02-18-SY-Photovoltaique.pdf",
  "windowRelation": "pre-window",
  "caveat": "ARIA covers classified installations and notable accidents, so small residential fires are under-represented; period predates the 2016+ incident window."
 },
 {
  "id": "uk-qbe-2024-breakdown",
  "jurisdiction": "United Kingdom",
  "period": "2024",
  "count": 151,
  "confirmedPvOrigin": null,
  "metric": "Solar-panel fires attended in 2024 across 37 of 49 fire services: 97 residential, 27 commercial, 17 solar farms (QBE FOI, submitted in planning evidence)",
  "sourceClass": "Insurer FOI data in planning evidence",
  "sourceTitle": "Planning Inspectorate submission EN010170: Fire Hazard and BESS installation proposals at Grendon",
  "sourceUrl": "https://nsip-documents.planninginspectorate.gov.uk/published-documents/EN010170-001692-Fire%20Hazard%20and%20BESS%20installation%20proposals%20at%20Grendon.pdf",
  "windowRelation": "within-window",
  "caveat": "Extends the QBE 2022–2024 series already tracked with a property-type breakdown for 2024; 12 fire services did not respond to the FOI."
 },
 {
  "id": "cea-global-rooftop-audit-2023",
  "jurisdiction": "Global (rooftop C&I audits)",
  "period": "to 2023",
  "count": 600,
  "confirmedPvOrigin": null,
  "metric": "Rooftop PV systems audited worldwide; 97% showed at least one major fire or electrical safety concern (49% grounding issues, 47% cross-mated connectors)",
  "sourceClass": "Independent engineering audit",
  "sourceTitle": "Clean Energy Associates: Top 10 PV Rooftop Safety Risks",
  "sourceUrl": "https://info.cea3.com/hubfs/PV%20Solar%20Safety%20Risks/CEA-Top%2010%20PV%20Rooftop%20Safety%20Risks.pdf",
  "windowRelation": "within-window",
  "caveat": "Audit sample skews to commercial and industrial rooftops whose owners commissioned inspections; findings are risk indicators, not fire counts."
 },
 {
  "id": "kwh-analytics-sra-2026",
  "jurisdiction": "United States (utility-scale)",
  "period": "2026 report",
  "count": null,
  "confirmedPvOrigin": null,
  "metric": "Fire identified as the second-largest loss driver at PV sites; 84% of PV fire events are equipment-driven brushfires originating within the plant",
  "sourceClass": "Insurance industry analysis",
  "sourceTitle": "kWh Analytics: 2026 Solar Risk Assessment",
  "sourceUrl": "https://kwhanalytics.com/industry-reports/2026-solar-risk-assessment/",
  "windowRelation": "within-window",
  "caveat": "Based on insured-loss and claims data for utility-scale assets; percentages describe loss events, not a census of all fires."
 },
 {
  "id": "iea-pvps-pvfs-2025",
  "jurisdiction": "International (IEA PVPS members)",
  "period": "2025 report",
  "count": null,
  "confirmedPvOrigin": null,
  "metric": "Photovoltaic Failure Fact Sheets cataloguing module and system failure modes, including those with fire consequences, from Task 13 field data",
  "sourceClass": "International research programme",
  "sourceTitle": "IEA PVPS Task 13: Photovoltaic Failure Fact Sheets (PVFS) 2025",
  "sourceUrl": "https://iea-pvps.org/wp-content/uploads/2025/02/IEA-PVPS-T13-30-2025-PVFS-ANNEX-Degradation-and-Failure.pdf",
  "windowRelation": "within-window",
  "caveat": "A failure-mode taxonomy rather than an incident census; fire-relevant failures are a subset of documented degradation modes."
 }
]